[
  {
    "addr1": "광주광역시 서구 서창둑길 377",
    "contentid": 2561700,
    "contenttypeid": "15",
    "firstimage": "http://tong.visitkorea.or.kr/cms/resource/06/2363006_image2_1.jpg",
    "mapx": 126.8287823667,
    "mapy": 35.1384854339,
    "title": "광주 서창 억새축제"
  },
  {
    "addr1": "울산광역시 남구 대공원로 84",
    "contentid": 130523,
    "contenttypeid": "14",
    "firstimage": "http://tong.visitkorea.or.kr/cms/resource/19/1899619_image2_1.jpg",
    "mapx": 129.2905556337,
    "mapy": 35.5319960593,
    "title": "가족문화센터"
  },
  {
    "addr1": "대구광역시 동구 공항로33길 21",
    "contentid": 132454,
    "contenttypeid": "38",
    "firstimage": "http://tong.visitkorea.or.kr/cms/resource/68/1970168_image2_1.jpg",
    "mapx": 128.6331251029,
    "mapy": 35.9029336186,
    "title": "대림목공예"
  },
  {
    "addr1": "전라남도 목포시 영산로29번길 6",
    "contentid": 2916281,
    "contenttypeid": "25",
    "firstimage": "http://tong.visitkorea.or.kr/cms/resource/17/2706017_image2_1.jpg",
    "mapx": 126.3821193361,
    "mapy": 34.7873731725,
    "title": "가을 바다를 즐길 수 있는 목포 1박2일 여행 코스"
  },
  {
    "addr1": "전라북도 남원시 요천로 1357",
    "contentid": 132464,
    "contenttypeid": "38",
    "firstimage": "http://tong.visitkorea.or.kr/cms/resource/50/1976550_image2_1.jpg",
    "mapx": 127.3718166509,
    "mapy": 35.3980653799,
    "title": "남원 목기공예사"
  },
  {
    "addr1": "경상남도 산청군 단성면 호암로 1325",
    "contentid": 132483,
    "contenttypeid": "38",
    "firstimage": "http://tong.visitkorea.or.kr/cms/resource/71/1979271_image2_1.jpg",
    "mapx": 127.9115644305,
    "mapy": 35.3623149902,
    "title": "웅석공방"
  },
  {
    "addr1": "서울특별시 강남구 압구정로12길 25",
    "contentid": 130424,
    "contenttypeid": "14",
    "firstimage": "http://tong.visitkorea.or.kr/cms/resource/18/684218_image2_1.jpg",
    "mapx": 127.0228904529,
    "mapy": 37.5222768521,
    "title": "UM갤러리"
  },
  {
    "addr1": "강원특별자치도 평창군 대관령면 대관령마루길 483-32",
    "contentid": 2672834,
    "contenttypeid": "25",
    "firstimage": "http://tong.visitkorea.or.kr/cms/resource/19/2640119_image2_1.bmp",
    "mapx": 128.7533288363,
    "mapy": 37.6876427505,
    "title": "봄 햇살 내리는 목장으로 초대"
  },
  {
    "addr1": "강원특별자치도 홍천군 홍천읍 갈마곡리",
    "contentid": 790124,
    "contenttypeid": "15",
    "firstimage": "http://tong.visitkorea.or.kr/cms/resource/95/2853995_image2_1.jpg",
    "mapx": 127.8931204292,
    "mapy": 37.6892539747,
    "title": "강원홍천 인삼∙한우 명품축제"
  }
]
